{"config":{"output_file":null,"full_docs":false,"pub_only":false,"reachable_only":false,"distro_crate":false,"signatures":false,"borrow_data":false},"version":"0.19.0","compilation":{"directory":"/Users/ryan/Documents/Learn/Rust/Programming Rust/02/iron-gcd","program":"/Users/ryan/.rustup/toolchains/nightly-x86_64-apple-darwin/bin/rls","arguments":[],"output":"/Users/ryan/Documents/Learn/Rust/Programming Rust/02/iron-gcd/target/rls/debug/deps/libiron_gcd-b40476597943c584.rmeta"},"prelude":{"crate_id":{"name":"iron_gcd","disambiguator":[8473612805531130855,16022279231162376055]},"crate_root":"src","external_crates":[{"file_name":"/Users/ryan/Documents/Learn/Rust/Programming Rust/02/iron-gcd/src/main.rs","num":1,"id":{"name":"std","disambiguator":[603768172935898252,12826861070591240039]}},{"file_name":"/Users/ryan/Documents/Learn/Rust/Programming Rust/02/iron-gcd/src/main.rs","num":2,"id":{"name":"core","disambiguator":[2815287589761039113,10394028720975510729]}},{"file_name":"/Users/ryan/Documents/Learn/Rust/Programming Rust/02/iron-gcd/src/main.rs","num":3,"id":{"name":"compiler_builtins","disambiguator":[2767677032142059259,16201317947151056619]}},{"file_name":"/Users/ryan/Documents/Learn/Rust/Programming Rust/02/iron-gcd/src/main.rs","num":4,"id":{"name":"rustc_std_workspace_core","disambiguator":[6569532271832813357,5558644548179987880]}},{"file_name":"/Users/ryan/Documents/Learn/Rust/Programming Rust/02/iron-gcd/src/main.rs","num":5,"id":{"name":"alloc","disambiguator":[15181256660015208263,13424169250424380958]}},{"file_name":"/Users/ryan/Documents/Learn/Rust/Programming Rust/02/iron-gcd/src/main.rs","num":6,"id":{"name":"libc","disambiguator":[14449708302553378442,6764885577286104745]}},{"file_name":"/Users/ryan/Documents/Learn/Rust/Programming Rust/02/iron-gcd/src/main.rs","num":7,"id":{"name":"unwind","disambiguator":[6031119962407932860,17656264859539038673]}},{"file_name":"/Users/ryan/Documents/Learn/Rust/Programming Rust/02/iron-gcd/src/main.rs","num":8,"id":{"name":"cfg_if","disambiguator":[808968361697194830,9958745973731971949]}},{"file_name":"/Users/ryan/Documents/Learn/Rust/Programming Rust/02/iron-gcd/src/main.rs","num":9,"id":{"name":"backtrace","disambiguator":[5829393040043201517,8019829011363502576]}},{"file_name":"/Users/ryan/Documents/Learn/Rust/Programming Rust/02/iron-gcd/src/main.rs","num":10,"id":{"name":"rustc_demangle","disambiguator":[12877238486384162475,10128020229416976087]}},{"file_name":"/Users/ryan/Documents/Learn/Rust/Programming Rust/02/iron-gcd/src/main.rs","num":11,"id":{"name":"backtrace_sys","disambiguator":[10813448863768151158,12612650826246199558]}},{"file_name":"/Users/ryan/Documents/Learn/Rust/Programming Rust/02/iron-gcd/src/main.rs","num":12,"id":{"name":"hashbrown","disambiguator":[1691828324011210183,9130257789058614790]}},{"file_name":"/Users/ryan/Documents/Learn/Rust/Programming Rust/02/iron-gcd/src/main.rs","num":13,"id":{"name":"rustc_std_workspace_alloc","disambiguator":[6501707610122218584,5103828404955810242]}},{"file_name":"/Users/ryan/Documents/Learn/Rust/Programming Rust/02/iron-gcd/src/main.rs","num":14,"id":{"name":"panic_unwind","disambiguator":[9512619531860128780,14710227587784000208]}},{"file_name":"/Users/ryan/Documents/Learn/Rust/Programming Rust/02/iron-gcd/src/main.rs","num":15,"id":{"name":"iron","disambiguator":[1561235956283235055,648217125874634515]}},{"file_name":"/Users/ryan/Documents/Learn/Rust/Programming Rust/02/iron-gcd/src/main.rs","num":16,"id":{"name":"log","disambiguator":[863419372294740889,16485189770945348507]}},{"file_name":"/Users/ryan/Documents/Learn/Rust/Programming Rust/02/iron-gcd/src/main.rs","num":17,"id":{"name":"log","disambiguator":[942694932642044366,7561146664581961228]}},{"file_name":"/Users/ryan/Documents/Learn/Rust/Programming Rust/02/iron-gcd/src/main.rs","num":18,"id":{"name":"cfg_if","disambiguator":[6762658599153071693,2937235755016515197]}},{"file_name":"/Users/ryan/Documents/Learn/Rust/Programming Rust/02/iron-gcd/src/main.rs","num":19,"id":{"name":"hyper","disambiguator":[12985986979644319060,16025394834466159229]}},{"file_name":"/Users/ryan/Documents/Learn/Rust/Programming Rust/02/iron-gcd/src/main.rs","num":20,"id":{"name":"base64","disambiguator":[13702019105500683088,10417502370768456312]}},{"file_name":"/Users/ryan/Documents/Learn/Rust/Programming Rust/02/iron-gcd/src/main.rs","num":21,"id":{"name":"byteorder","disambiguator":[9930209339847118083,17685717341201041387]}},{"file_name":"/Users/ryan/Documents/Learn/Rust/Programming Rust/02/iron-gcd/src/main.rs","num":22,"id":{"name":"safemem","disambiguator":[1321843377983387217,17853106749718940919]}},{"file_name":"/Users/ryan/Documents/Learn/Rust/Programming Rust/02/iron-gcd/src/main.rs","num":23,"id":{"name":"time","disambiguator":[12818342496264019847,3981305861312621931]}},{"file_name":"/Users/ryan/Documents/Learn/Rust/Programming Rust/02/iron-gcd/src/main.rs","num":24,"id":{"name":"libc","disambiguator":[16061977405667077820,6504061404778655613]}},{"file_name":"/Users/ryan/Documents/Learn/Rust/Programming Rust/02/iron-gcd/src/main.rs","num":25,"id":{"name":"url","disambiguator":[5361667711373699495,75734708822919041]}},{"file_name":"/Users/ryan/Documents/Learn/Rust/Programming Rust/02/iron-gcd/src/main.rs","num":26,"id":{"name":"matches","disambiguator":[5278987446623513357,1943597464061273226]}},{"file_name":"/Users/ryan/Documents/Learn/Rust/Programming Rust/02/iron-gcd/src/main.rs","num":27,"id":{"name":"idna","disambiguator":[18117387827148945670,8068842770045313247]}},{"file_name":"/Users/ryan/Documents/Learn/Rust/Programming Rust/02/iron-gcd/src/main.rs","num":28,"id":{"name":"unicode_bidi","disambiguator":[13807336520544506707,13519015036261908912]}},{"file_name":"/Users/ryan/Documents/Learn/Rust/Programming Rust/02/iron-gcd/src/main.rs","num":29,"id":{"name":"unicode_normalization","disambiguator":[3220058951226116582,16674090537398625463]}},{"file_name":"/Users/ryan/Documents/Learn/Rust/Programming Rust/02/iron-gcd/src/main.rs","num":30,"id":{"name":"smallvec","disambiguator":[1089915960094613685,15560854074770010004]}},{"file_name":"/Users/ryan/Documents/Learn/Rust/Programming Rust/02/iron-gcd/src/main.rs","num":31,"id":{"name":"percent_encoding","disambiguator":[8841960619296764232,17818171299364570749]}},{"file_name":"/Users/ryan/Documents/Learn/Rust/Programming Rust/02/iron-gcd/src/main.rs","num":32,"id":{"name":"unicase","disambiguator":[4099603166580540136,2921546406620226400]}},{"file_name":"/Users/ryan/Documents/Learn/Rust/Programming Rust/02/iron-gcd/src/main.rs","num":33,"id":{"name":"httparse","disambiguator":[4420661458647161965,13275281941164324106]}},{"file_name":"/Users/ryan/Documents/Learn/Rust/Programming Rust/02/iron-gcd/src/main.rs","num":34,"id":{"name":"num_cpus","disambiguator":[11566884666533389490,4888800946641971600]}},{"file_name":"/Users/ryan/Documents/Learn/Rust/Programming Rust/02/iron-gcd/src/main.rs","num":35,"id":{"name":"traitobject","disambiguator":[16040701344157170059,3674145677216505911]}},{"file_name":"/Users/ryan/Documents/Learn/Rust/Programming Rust/02/iron-gcd/src/main.rs","num":36,"id":{"name":"typeable","disambiguator":[16406330774703205232,17712211597833701089]}},{"file_name":"/Users/ryan/Documents/Learn/Rust/Programming Rust/02/iron-gcd/src/main.rs","num":37,"id":{"name":"language_tags","disambiguator":[7669027334417166834,6415607730132204849]}},{"file_name":"/Users/ryan/Documents/Learn/Rust/Programming Rust/02/iron-gcd/src/main.rs","num":38,"id":{"name":"mime","disambiguator":[7853794497421827632,2245565105490922042]}},{"file_name":"/Users/ryan/Documents/Learn/Rust/Programming Rust/02/iron-gcd/src/main.rs","num":39,"id":{"name":"typemap","disambiguator":[4342910116112114689,4805652522626956517]}},{"file_name":"/Users/ryan/Documents/Learn/Rust/Programming Rust/02/iron-gcd/src/main.rs","num":40,"id":{"name":"unsafe_any","disambiguator":[17615910499773017374,17509810526377767482]}},{"file_name":"/Users/ryan/Documents/Learn/Rust/Programming Rust/02/iron-gcd/src/main.rs","num":41,"id":{"name":"plugin","disambiguator":[3822183953515552767,14539658496233188474]}},{"file_name":"/Users/ryan/Documents/Learn/Rust/Programming Rust/02/iron-gcd/src/main.rs","num":42,"id":{"name":"error","disambiguator":[8641365744260987860,14923902456694180877]}},{"file_name":"/Users/ryan/Documents/Learn/Rust/Programming Rust/02/iron-gcd/src/main.rs","num":43,"id":{"name":"conduit_mime_types","disambiguator":[10794501858956796679,17694625745357056756]}},{"file_name":"/Users/ryan/Documents/Learn/Rust/Programming Rust/02/iron-gcd/src/main.rs","num":44,"id":{"name":"rustc_serialize","disambiguator":[1236005731191830620,3512856864337357337]}},{"file_name":"/Users/ryan/Documents/Learn/Rust/Programming Rust/02/iron-gcd/src/main.rs","num":45,"id":{"name":"lazy_static","disambiguator":[8833918882273208666,7262364252078586868]}},{"file_name":"/Users/ryan/Documents/Learn/Rust/Programming Rust/02/iron-gcd/src/main.rs","num":46,"id":{"name":"modifier","disambiguator":[10115156882074154531,10724872349227122470]}},{"file_name":"/Users/ryan/Documents/Learn/Rust/Programming Rust/02/iron-gcd/src/main.rs","num":47,"id":{"name":"router","disambiguator":[10670943714283123622,12624305181385535343]}},{"file_name":"/Users/ryan/Documents/Learn/Rust/Programming Rust/02/iron-gcd/src/main.rs","num":48,"id":{"name":"route_recognizer","disambiguator":[18362168052227587599,11963372190588620258]}},{"file_name":"/Users/ryan/Documents/Learn/Rust/Programming Rust/02/iron-gcd/src/main.rs","num":49,"id":{"name":"urlencoded","disambiguator":[17993307424686873128,13946630851420210602]}},{"file_name":"/Users/ryan/Documents/Learn/Rust/Programming Rust/02/iron-gcd/src/main.rs","num":50,"id":{"name":"bodyparser","disambiguator":[2310668370284110722,14084798479242245835]}},{"file_name":"/Users/ryan/Documents/Learn/Rust/Programming Rust/02/iron-gcd/src/main.rs","num":51,"id":{"name":"persistent","disambiguator":[14163433930356966347,15877902195229633403]}},{"file_name":"/Users/ryan/Documents/Learn/Rust/Programming Rust/02/iron-gcd/src/main.rs","num":52,"id":{"name":"serde","disambiguator":[2065825398170245575,4202017623761558930]}},{"file_name":"/Users/ryan/Documents/Learn/Rust/Programming Rust/02/iron-gcd/src/main.rs","num":53,"id":{"name":"serde_json","disambiguator":[8500669828094709726,687101836144065781]}},{"file_name":"/Users/ryan/Documents/Learn/Rust/Programming Rust/02/iron-gcd/src/main.rs","num":54,"id":{"name":"num_traits","disambiguator":[12550421991874115730,13559162161898778833]}},{"file_name":"/Users/ryan/Documents/Learn/Rust/Programming Rust/02/iron-gcd/src/main.rs","num":55,"id":{"name":"num_traits","disambiguator":[10255955740324190323,1214112512415152489]}},{"file_name":"/Users/ryan/Documents/Learn/Rust/Programming Rust/02/iron-gcd/src/main.rs","num":56,"id":{"name":"itoa","disambiguator":[1594630348928956006,9713326411090900177]}},{"file_name":"/Users/ryan/Documents/Learn/Rust/Programming Rust/02/iron-gcd/src/main.rs","num":57,"id":{"name":"dtoa","disambiguator":[12712760531747354134,15000648337969121042]}}],"span":{"file_name":"src/main.rs","byte_start":0,"byte_end":2519,"line_start":1,"line_end":91,"column_start":1,"column_end":2}},"imports":[{"kind":"ExternCrate","ref_id":null,"span":{"file_name":"src/main.rs","byte_start":13,"byte_end":17,"line_start":1,"line_end":1,"column_start":14,"column_end":18},"alias_span":null,"name":"iron","value":"","parent":{"krate":0,"index":0}},{"kind":"ExternCrate","ref_id":null,"span":{"file_name":"src/main.rs","byte_start":45,"byte_end":49,"line_start":2,"line_end":2,"column_start":27,"column_end":31},"alias_span":null,"name":"mime","value":"","parent":{"krate":0,"index":0}},{"kind":"ExternCrate","ref_id":null,"span":{"file_name":"src/main.rs","byte_start":64,"byte_end":70,"line_start":3,"line_end":3,"column_start":14,"column_end":20},"alias_span":null,"name":"router","value":"","parent":{"krate":0,"index":0}},{"kind":"ExternCrate","ref_id":null,"span":{"file_name":"src/main.rs","byte_start":85,"byte_end":95,"line_start":4,"line_end":4,"column_start":14,"column_end":24},"alias_span":null,"name":"urlencoded","value":"","parent":{"krate":0,"index":0}},{"kind":"GlobUse","ref_id":null,"span":{"file_name":"src/main.rs","byte_start":117,"byte_end":118,"line_start":6,"line_end":6,"column_start":20,"column_end":21},"alias_span":null,"name":"*","value":"IronResult, Set, Plugin, Request, Response, Iron","parent":{"krate":0,"index":0}},{"kind":"Use","ref_id":{"krate":15,"index":70},"span":{"file_name":"src/main.rs","byte_start":130,"byte_end":136,"line_start":7,"line_end":7,"column_start":11,"column_end":17},"alias_span":null,"name":"status","value":"","parent":{"krate":0,"index":0}},{"kind":"Use","ref_id":{"krate":47,"index":37},"span":{"file_name":"src/main.rs","byte_start":150,"byte_end":156,"line_start":8,"line_end":8,"column_start":13,"column_end":19},"alias_span":null,"name":"Router","value":"","parent":{"krate":0,"index":0}},{"kind":"Use","ref_id":{"krate":2,"index":6753},"span":{"file_name":"src/main.rs","byte_start":172,"byte_end":179,"line_start":9,"line_end":9,"column_start":15,"column_end":22},"alias_span":null,"name":"FromStr","value":"","parent":{"krate":0,"index":0}},{"kind":"Use","ref_id":{"krate":49,"index":16},"span":{"file_name":"src/main.rs","byte_start":197,"byte_end":211,"line_start":10,"line_end":10,"column_start":17,"column_end":31},"alias_span":null,"name":"UrlEncodedBody","value":"","parent":{"krate":0,"index":0}}],"defs":[{"kind":"Mod","id":{"krate":0,"index":0},"span":{"file_name":"src/main.rs","byte_start":0,"byte_end":2519,"line_start":1,"line_end":91,"column_start":1,"column_end":2},"name":"","qualname":"::","value":"src/main.rs","parent":null,"children":[{"krate":0,"index":1},{"krate":0,"index":2},{"krate":0,"index":3},{"krate":0,"index":4},{"krate":0,"index":5},{"krate":0,"index":6},{"krate":0,"index":7},{"krate":0,"index":8},{"krate":0,"index":9},{"krate":0,"index":10},{"krate":0,"index":11},{"krate":0,"index":12},{"krate":0,"index":13},{"krate":0,"index":14},{"krate":0,"index":15}],"decl_id":null,"docs":"","sig":null,"attributes":[]},{"kind":"Local","id":{"krate":0,"index":4294967254},"span":{"file_name":"src/main.rs","byte_start":225,"byte_end":226,"line_start":12,"line_end":12,"column_start":12,"column_end":13},"name":"n","qualname":"::gcd::n","value":"u64","parent":null,"children":[],"decl_id":null,"docs":"","sig":null,"attributes":[]},{"kind":"Local","id":{"krate":0,"index":4294967250},"span":{"file_name":"src/main.rs","byte_start":237,"byte_end":238,"line_start":12,"line_end":12,"column_start":24,"column_end":25},"name":"m","qualname":"::gcd::m","value":"u64","parent":null,"children":[],"decl_id":null,"docs":"","sig":null,"attributes":[]},{"kind":"Function","id":{"krate":0,"index":12},"span":{"file_name":"src/main.rs","byte_start":217,"byte_end":220,"line_start":12,"line_end":12,"column_start":4,"column_end":7},"name":"gcd","qualname":"::gcd","value":"fn (mut n: u64, mut m: u64) -> u64","parent":null,"children":[],"decl_id":null,"docs":"","sig":null,"attributes":[]},{"kind":"Local","id":{"krate":0,"index":4294967232},"span":{"file_name":"src/main.rs","byte_start":339,"byte_end":340,"line_start":16,"line_end":16,"column_start":17,"column_end":18},"name":"t","qualname":"t$63","value":"u64","parent":null,"children":[],"decl_id":null,"docs":"","sig":null,"attributes":[]},{"kind":"Local","id":{"krate":0,"index":4294967205},"span":{"file_name":"src/main.rs","byte_start":440,"byte_end":448,"line_start":25,"line_end":25,"column_start":13,"column_end":21},"name":"_request","qualname":"::get_form::_request","value":"&mut iron::Request<'_, '_>","parent":null,"children":[],"decl_id":null,"docs":"","sig":null,"attributes":[]},{"kind":"Function","id":{"krate":0,"index":13},"span":{"file_name":"src/main.rs","byte_start":431,"byte_end":439,"line_start":25,"line_end":25,"column_start":4,"column_end":12},"name":"get_form","qualname":"::get_form","value":"fn (_request: &mut Request) -> IronResult<Response>","parent":null,"children":[],"decl_id":null,"docs":"","sig":null,"attributes":[]},{"kind":"Local","id":{"krate":0,"index":4294967195},"span":{"file_name":"src/main.rs","byte_start":502,"byte_end":510,"line_start":26,"line_end":26,"column_start":13,"column_end":21},"name":"response","qualname":"response$100","value":"iron::Response","parent":null,"children":[],"decl_id":null,"docs":"","sig":null,"attributes":[]},{"kind":"Local","id":{"krate":0,"index":4294967167},"span":{"file_name":"src/main.rs","byte_start":922,"byte_end":929,"line_start":42,"line_end":42,"column_start":13,"column_end":20},"name":"request","qualname":"::post_gcd::request","value":"&mut iron::Request<'_, '_>","parent":null,"children":[],"decl_id":null,"docs":"","sig":null,"attributes":[]},{"kind":"Function","id":{"krate":0,"index":14},"span":{"file_name":"src/main.rs","byte_start":913,"byte_end":921,"line_start":42,"line_end":42,"column_start":4,"column_end":12},"name":"post_gcd","qualname":"::post_gcd","value":"fn (request: &mut Request) -> IronResult<Response>","parent":null,"children":[],"decl_id":null,"docs":"","sig":null,"attributes":[]},{"kind":"Local","id":{"krate":0,"index":4294967157},"span":{"file_name":"src/main.rs","byte_start":983,"byte_end":991,"line_start":43,"line_end":43,"column_start":13,"column_end":21},"name":"response","qualname":"response$138","value":"iron::Response","parent":null,"children":[],"decl_id":null,"docs":"","sig":null,"attributes":[]},{"kind":"Local","id":{"krate":0,"index":4294967151},"span":{"file_name":"src/main.rs","byte_start":1020,"byte_end":1029,"line_start":45,"line_end":45,"column_start":9,"column_end":18},"name":"form_data","qualname":"form_data$144","value":"&std::collections::HashMap<std::string::String, std::vec::Vec<std::string::String>>","parent":null,"children":[],"decl_id":null,"docs":"","sig":null,"attributes":[]},{"kind":"Local","id":{"krate":0,"index":4294967141},"span":{"file_name":"src/main.rs","byte_start":1088,"byte_end":1089,"line_start":46,"line_end":46,"column_start":13,"column_end":14},"name":"e","qualname":"e$154","value":"urlencoded::UrlDecodingError","parent":null,"children":[],"decl_id":null,"docs":"","sig":null,"attributes":[]},{"kind":"Local","id":{"krate":0,"index":4294967118},"span":{"file_name":"src/main.rs","byte_start":1277,"byte_end":1280,"line_start":51,"line_end":51,"column_start":12,"column_end":15},"name":"map","qualname":"map$177","value":"&std::collections::HashMap<std::string::String, std::vec::Vec<std::string::String>>","parent":null,"children":[],"decl_id":null,"docs":"","sig":null,"attributes":[]},{"kind":"Local","id":{"krate":0,"index":4294967113},"span":{"file_name":"src/main.rs","byte_start":1304,"byte_end":1320,"line_start":53,"line_end":53,"column_start":9,"column_end":25},"name":"unparsed_numbers","qualname":"unparsed_numbers$182","value":"&std::vec::Vec<std::string::String>","parent":null,"children":[],"decl_id":null,"docs":"","sig":null,"attributes":[]},{"kind":"Local","id":{"krate":0,"index":4294967083},"span":{"file_name":"src/main.rs","byte_start":1549,"byte_end":1553,"line_start":59,"line_end":59,"column_start":14,"column_end":18},"name":"nums","qualname":"nums$212","value":"&std::vec::Vec<std::string::String>","parent":null,"children":[],"decl_id":null,"docs":"","sig":null,"attributes":[]},{"kind":"Local","id":{"krate":0,"index":4294967078},"span":{"file_name":"src/main.rs","byte_start":1582,"byte_end":1589,"line_start":61,"line_end":61,"column_start":13,"column_end":20},"name":"numbers","qualname":"numbers$217","value":"std::vec::Vec<u64>","parent":null,"children":[],"decl_id":null,"docs":"","sig":null,"attributes":[]},{"kind":"Local","id":{"krate":0,"index":4294967073},"span":{"file_name":"src/main.rs","byte_start":1612,"byte_end":1620,"line_start":62,"line_end":62,"column_start":9,"column_end":17},"name":"unparsed","qualname":"unparsed$222","value":"&std::string::String","parent":null,"children":[],"decl_id":null,"docs":"","sig":null,"attributes":[]},{"kind":"Local","id":{"krate":0,"index":4294967036},"span":{"file_name":"src/main.rs","byte_start":1929,"byte_end":1930,"line_start":69,"line_end":69,"column_start":16,"column_end":17},"name":"n","qualname":"n$259","value":"u64","parent":null,"children":[],"decl_id":null,"docs":"","sig":null,"attributes":[]},{"kind":"Local","id":{"krate":0,"index":4294967024},"span":{"file_name":"src/main.rs","byte_start":1985,"byte_end":1986,"line_start":73,"line_end":73,"column_start":13,"column_end":14},"name":"d","qualname":"d$271","value":"u64","parent":null,"children":[],"decl_id":null,"docs":"","sig":null,"attributes":[]},{"kind":"Local","id":{"krate":0,"index":4294967019},"span":{"file_name":"src/main.rs","byte_start":2009,"byte_end":2010,"line_start":74,"line_end":74,"column_start":9,"column_end":10},"name":"m","qualname":"m$276","value":"&u64","parent":null,"children":[],"decl_id":null,"docs":"","sig":null,"attributes":[]},{"kind":"Function","id":{"krate":0,"index":15},"span":{"file_name":"src/main.rs","byte_start":2281,"byte_end":2285,"line_start":84,"line_end":84,"column_start":4,"column_end":8},"name":"main","qualname":"::main","value":"fn () -> ()","parent":null,"children":[],"decl_id":null,"docs":"","sig":null,"attributes":[]},{"kind":"Local","id":{"krate":0,"index":4294966976},"span":{"file_name":"src/main.rs","byte_start":2302,"byte_end":2308,"line_start":85,"line_end":85,"column_start":13,"column_end":19},"name":"router","qualname":"router$319","value":"router::Router","parent":null,"children":[],"decl_id":null,"docs":"","sig":null,"attributes":[]}],"impls":[],"refs":[{"kind":"Mod","span":{"file_name":"src/main.rs","byte_start":102,"byte_end":106,"line_start":6,"line_end":6,"column_start":5,"column_end":9},"ref_id":{"krate":15,"index":0}},{"kind":"Mod","span":{"file_name":"src/main.rs","byte_start":108,"byte_end":115,"line_start":6,"line_end":6,"column_start":11,"column_end":18},"ref_id":{"krate":15,"index":51}},{"kind":"Mod","span":{"file_name":"src/main.rs","byte_start":124,"byte_end":128,"line_start":7,"line_end":7,"column_start":5,"column_end":9},"ref_id":{"krate":15,"index":0}},{"kind":"Mod","span":{"file_name":"src/main.rs","byte_start":142,"byte_end":148,"line_start":8,"line_end":8,"column_start":5,"column_end":11},"ref_id":{"krate":47,"index":0}},{"kind":"Mod","span":{"file_name":"src/main.rs","byte_start":162,"byte_end":165,"line_start":9,"line_end":9,"column_start":5,"column_end":8},"ref_id":{"krate":1,"index":0}},{"kind":"Mod","span":{"file_name":"src/main.rs","byte_start":167,"byte_end":170,"line_start":9,"line_end":9,"column_start":10,"column_end":13},"ref_id":{"krate":5,"index":3414}},{"kind":"Mod","span":{"file_name":"src/main.rs","byte_start":185,"byte_end":195,"line_start":10,"line_end":10,"column_start":5,"column_end":15},"ref_id":{"krate":49,"index":0}},{"kind":"Variable","span":{"file_name":"src/main.rs","byte_start":266,"byte_end":267,"line_start":13,"line_end":13,"column_start":13,"column_end":14},"ref_id":{"krate":0,"index":4294967254}},{"kind":"Variable","span":{"file_name":"src/main.rs","byte_start":276,"byte_end":277,"line_start":13,"line_end":13,"column_start":23,"column_end":24},"ref_id":{"krate":0,"index":4294967250}},{"kind":"Variable","span":{"file_name":"src/main.rs","byte_start":295,"byte_end":296,"line_start":14,"line_end":14,"column_start":11,"column_end":12},"ref_id":{"krate":0,"index":4294967250}},{"kind":"Variable","span":{"file_name":"src/main.rs","byte_start":315,"byte_end":316,"line_start":15,"line_end":15,"column_start":12,"column_end":13},"ref_id":{"krate":0,"index":4294967250}},{"kind":"Variable","span":{"file_name":"src/main.rs","byte_start":319,"byte_end":320,"line_start":15,"line_end":15,"column_start":16,"column_end":17},"ref_id":{"krate":0,"index":4294967254}},{"kind":"Variable","span":{"file_name":"src/main.rs","byte_start":343,"byte_end":344,"line_start":16,"line_end":16,"column_start":21,"column_end":22},"ref_id":{"krate":0,"index":4294967250}},{"kind":"Variable","span":{"file_name":"src/main.rs","byte_start":358,"byte_end":359,"line_start":17,"line_end":17,"column_start":13,"column_end":14},"ref_id":{"krate":0,"index":4294967250}},{"kind":"Variable","span":{"file_name":"src/main.rs","byte_start":362,"byte_end":363,"line_start":17,"line_end":17,"column_start":17,"column_end":18},"ref_id":{"krate":0,"index":4294967254}},{"kind":"Variable","span":{"file_name":"src/main.rs","byte_start":377,"byte_end":378,"line_start":18,"line_end":18,"column_start":13,"column_end":14},"ref_id":{"krate":0,"index":4294967254}},{"kind":"Variable","span":{"file_name":"src/main.rs","byte_start":381,"byte_end":382,"line_start":18,"line_end":18,"column_start":17,"column_end":18},"ref_id":{"krate":0,"index":4294967232}},{"kind":"Variable","span":{"file_name":"src/main.rs","byte_start":402,"byte_end":403,"line_start":20,"line_end":20,"column_start":9,"column_end":10},"ref_id":{"krate":0,"index":4294967250}},{"kind":"Variable","span":{"file_name":"src/main.rs","byte_start":406,"byte_end":407,"line_start":20,"line_end":20,"column_start":13,"column_end":14},"ref_id":{"krate":0,"index":4294967250}},{"kind":"Variable","span":{"file_name":"src/main.rs","byte_start":410,"byte_end":411,"line_start":20,"line_end":20,"column_start":17,"column_end":18},"ref_id":{"krate":0,"index":4294967254}},{"kind":"Variable","span":{"file_name":"src/main.rs","byte_start":423,"byte_end":424,"line_start":22,"line_end":22,"column_start":5,"column_end":6},"ref_id":{"krate":0,"index":4294967254}},{"kind":"Type","span":{"file_name":"src/main.rs","byte_start":455,"byte_end":462,"line_start":25,"line_end":25,"column_start":28,"column_end":35},"ref_id":{"krate":15,"index":271}},{"kind":"Type","span":{"file_name":"src/main.rs","byte_start":467,"byte_end":477,"line_start":25,"line_end":25,"column_start":40,"column_end":50},"ref_id":{"krate":15,"index":49}},{"kind":"Type","span":{"file_name":"src/main.rs","byte_start":478,"byte_end":486,"line_start":25,"line_end":25,"column_start":51,"column_end":59},"ref_id":{"krate":15,"index":197}},{"kind":"Function","span":{"file_name":"src/main.rs","byte_start":523,"byte_end":526,"line_start":26,"line_end":26,"column_start":34,"column_end":37},"ref_id":{"krate":15,"index":203}},{"kind":"Type","span":{"file_name":"src/main.rs","byte_start":513,"byte_end":521,"line_start":26,"line_end":26,"column_start":24,"column_end":32},"ref_id":{"krate":15,"index":197}},{"kind":"Function","span":{"file_name":"src/main.rs","byte_start":544,"byte_end":551,"line_start":28,"line_end":28,"column_start":14,"column_end":21},"ref_id":{"krate":46,"index":9}},{"kind":"Variable","span":{"file_name":"src/main.rs","byte_start":535,"byte_end":543,"line_start":28,"line_end":28,"column_start":5,"column_end":13},"ref_id":{"krate":0,"index":4294967195}},{"kind":"Variable","span":{"file_name":"src/main.rs","byte_start":560,"byte_end":562,"line_start":28,"line_end":28,"column_start":30,"column_end":32},"ref_id":{"krate":19,"index":4475}},{"kind":"Mod","span":{"file_name":"src/main.rs","byte_start":552,"byte_end":558,"line_start":28,"line_end":28,"column_start":22,"column_end":28},"ref_id":{"krate":15,"index":70}},{"kind":"Function","span":{"file_name":"src/main.rs","byte_start":578,"byte_end":585,"line_start":29,"line_end":29,"column_start":14,"column_end":21},"ref_id":{"krate":46,"index":9}},{"kind":"Variable","span":{"file_name":"src/main.rs","byte_start":569,"byte_end":577,"line_start":29,"line_end":29,"column_start":5,"column_end":13},"ref_id":{"krate":0,"index":4294967195}},{"kind":"Function","span":{"file_name":"src/main.rs","byte_start":632,"byte_end":639,"line_start":30,"line_end":30,"column_start":14,"column_end":21},"ref_id":{"krate":46,"index":9}},{"kind":"Variable","span":{"file_name":"src/main.rs","byte_start":623,"byte_end":631,"line_start":30,"line_end":30,"column_start":5,"column_end":13},"ref_id":{"krate":0,"index":4294967195}},{"kind":"Variable","span":{"file_name":"src/main.rs","byte_start":894,"byte_end":896,"line_start":39,"line_end":39,"column_start":5,"column_end":7},"ref_id":{"krate":2,"index":29413}},{"kind":"Variable","span":{"file_name":"src/main.rs","byte_start":897,"byte_end":905,"line_start":39,"line_end":39,"column_start":8,"column_end":16},"ref_id":{"krate":0,"index":4294967195}},{"kind":"Type","span":{"file_name":"src/main.rs","byte_start":936,"byte_end":943,"line_start":42,"line_end":42,"column_start":27,"column_end":34},"ref_id":{"krate":15,"index":271}},{"kind":"Type","span":{"file_name":"src/main.rs","byte_start":948,"byte_end":958,"line_start":42,"line_end":42,"column_start":39,"column_end":49},"ref_id":{"krate":15,"index":49}},{"kind":"Type","span":{"file_name":"src/main.rs","byte_start":959,"byte_end":967,"line_start":42,"line_end":42,"column_start":50,"column_end":58},"ref_id":{"krate":15,"index":197}},{"kind":"Function","span":{"file_name":"src/main.rs","byte_start":1004,"byte_end":1007,"line_start":43,"line_end":43,"column_start":34,"column_end":37},"ref_id":{"krate":15,"index":203}},{"kind":"Type","span":{"file_name":"src/main.rs","byte_start":994,"byte_end":1002,"line_start":43,"line_end":43,"column_start":24,"column_end":32},"ref_id":{"krate":15,"index":197}},{"kind":"Function","span":{"file_name":"src/main.rs","byte_start":1046,"byte_end":1053,"line_start":45,"line_end":45,"column_start":35,"column_end":42},"ref_id":{"krate":41,"index":19}},{"kind":"Type","span":{"file_name":"src/main.rs","byte_start":1056,"byte_end":1070,"line_start":45,"line_end":45,"column_start":45,"column_end":59},"ref_id":{"krate":49,"index":16}},{"kind":"Variable","span":{"file_name":"src/main.rs","byte_start":1038,"byte_end":1045,"line_start":45,"line_end":45,"column_start":27,"column_end":34},"ref_id":{"krate":0,"index":4294967167}},{"kind":"Variable","span":{"file_name":"src/main.rs","byte_start":1084,"byte_end":1087,"line_start":46,"line_end":46,"column_start":9,"column_end":12},"ref_id":{"krate":2,"index":29416}},{"kind":"Variable","span":{"file_name":"src/main.rs","byte_start":1084,"byte_end":1087,"line_start":46,"line_end":46,"column_start":9,"column_end":12},"ref_id":{"krate":2,"index":29416}},{"kind":"Function","span":{"file_name":"src/main.rs","byte_start":1117,"byte_end":1124,"line_start":47,"line_end":47,"column_start":22,"column_end":29},"ref_id":{"krate":46,"index":9}},{"kind":"Variable","span":{"file_name":"src/main.rs","byte_start":1108,"byte_end":1116,"line_start":47,"line_end":47,"column_start":13,"column_end":21},"ref_id":{"krate":0,"index":4294967157}},{"kind":"Variable","span":{"file_name":"src/main.rs","byte_start":1133,"byte_end":1143,"line_start":47,"line_end":47,"column_start":38,"column_end":48},"ref_id":{"krate":19,"index":4511}},{"kind":"Mod","span":{"file_name":"src/main.rs","byte_start":1125,"byte_end":1131,"line_start":47,"line_end":47,"column_start":30,"column_end":36},"ref_id":{"krate":15,"index":70}},{"kind":"Function","span":{"file_name":"src/main.rs","byte_start":1167,"byte_end":1174,"line_start":48,"line_end":48,"column_start":22,"column_end":29},"ref_id":{"krate":46,"index":9}},{"kind":"Variable","span":{"file_name":"src/main.rs","byte_start":1158,"byte_end":1166,"line_start":48,"line_end":48,"column_start":13,"column_end":21},"ref_id":{"krate":0,"index":4294967157}},{"kind":"Variable","span":{"file_name":"src/main.rs","byte_start":1218,"byte_end":1219,"line_start":48,"line_end":48,"column_start":73,"column_end":74},"ref_id":{"krate":0,"index":4294967141}},{"kind":"Variable","span":{"file_name":"src/main.rs","byte_start":1242,"byte_end":1244,"line_start":49,"line_end":49,"column_start":20,"column_end":22},"ref_id":{"krate":2,"index":29413}},{"kind":"Variable","span":{"file_name":"src/main.rs","byte_start":1245,"byte_end":1253,"line_start":49,"line_end":49,"column_start":23,"column_end":31},"ref_id":{"krate":0,"index":4294967157}},{"kind":"Variable","span":{"file_name":"src/main.rs","byte_start":1274,"byte_end":1276,"line_start":51,"line_end":51,"column_start":9,"column_end":11},"ref_id":{"krate":2,"index":29413}},{"kind":"Variable","span":{"file_name":"src/main.rs","byte_start":1274,"byte_end":1276,"line_start":51,"line_end":51,"column_start":9,"column_end":11},"ref_id":{"krate":2,"index":29413}},{"kind":"Variable","span":{"file_name":"src/main.rs","byte_start":1285,"byte_end":1288,"line_start":51,"line_end":51,"column_start":20,"column_end":23},"ref_id":{"krate":0,"index":4294967118}},{"kind":"Function","span":{"file_name":"src/main.rs","byte_start":1339,"byte_end":1342,"line_start":53,"line_end":53,"column_start":44,"column_end":47},"ref_id":{"krate":1,"index":632}},{"kind":"Variable","span":{"file_name":"src/main.rs","byte_start":1329,"byte_end":1338,"line_start":53,"line_end":53,"column_start":34,"column_end":43},"ref_id":{"krate":0,"index":4294967151}},{"kind":"Variable","span":{"file_name":"src/main.rs","byte_start":1358,"byte_end":1362,"line_start":54,"line_end":54,"column_start":9,"column_end":13},"ref_id":{"krate":2,"index":29315}},{"kind":"Function","span":{"file_name":"src/main.rs","byte_start":1389,"byte_end":1396,"line_start":55,"line_end":55,"column_start":22,"column_end":29},"ref_id":{"krate":46,"index":9}},{"kind":"Variable","span":{"file_name":"src/main.rs","byte_start":1380,"byte_end":1388,"line_start":55,"line_end":55,"column_start":13,"column_end":21},"ref_id":{"krate":0,"index":4294967157}},{"kind":"Variable","span":{"file_name":"src/main.rs","byte_start":1405,"byte_end":1415,"line_start":55,"line_end":55,"column_start":38,"column_end":48},"ref_id":{"krate":19,"index":4511}},{"kind":"Mod","span":{"file_name":"src/main.rs","byte_start":1397,"byte_end":1403,"line_start":55,"line_end":55,"column_start":30,"column_end":36},"ref_id":{"krate":15,"index":70}},{"kind":"Function","span":{"file_name":"src/main.rs","byte_start":1439,"byte_end":1446,"line_start":56,"line_end":56,"column_start":22,"column_end":29},"ref_id":{"krate":46,"index":9}},{"kind":"Variable","span":{"file_name":"src/main.rs","byte_start":1430,"byte_end":1438,"line_start":56,"line_end":56,"column_start":13,"column_end":21},"ref_id":{"krate":0,"index":4294967157}},{"kind":"Variable","span":{"file_name":"src/main.rs","byte_start":1512,"byte_end":1514,"line_start":57,"line_end":57,"column_start":20,"column_end":22},"ref_id":{"krate":2,"index":29413}},{"kind":"Variable","span":{"file_name":"src/main.rs","byte_start":1515,"byte_end":1523,"line_start":57,"line_end":57,"column_start":23,"column_end":31},"ref_id":{"krate":0,"index":4294967157}},{"kind":"Variable","span":{"file_name":"src/main.rs","byte_start":1544,"byte_end":1548,"line_start":59,"line_end":59,"column_start":9,"column_end":13},"ref_id":{"krate":2,"index":29317}},{"kind":"Variable","span":{"file_name":"src/main.rs","byte_start":1544,"byte_end":1548,"line_start":59,"line_end":59,"column_start":9,"column_end":13},"ref_id":{"krate":2,"index":29317}},{"kind":"Variable","span":{"file_name":"src/main.rs","byte_start":1558,"byte_end":1562,"line_start":59,"line_end":59,"column_start":23,"column_end":27},"ref_id":{"krate":0,"index":4294967083}},{"kind":"Function","span":{"file_name":"src/main.rs","byte_start":1597,"byte_end":1600,"line_start":61,"line_end":61,"column_start":28,"column_end":31},"ref_id":{"krate":5,"index":3835}},{"kind":"Type","span":{"file_name":"src/main.rs","byte_start":1592,"byte_end":1595,"line_start":61,"line_end":61,"column_start":23,"column_end":26},"ref_id":{"krate":5,"index":3829}},{"kind":"Variable","span":{"file_name":"src/main.rs","byte_start":1624,"byte_end":1640,"line_start":62,"line_end":62,"column_start":21,"column_end":37},"ref_id":{"krate":0,"index":4294967113}},{"kind":"Function","span":{"file_name":"src/main.rs","byte_start":1662,"byte_end":1670,"line_start":63,"line_end":63,"column_start":20,"column_end":28},"ref_id":{"krate":2,"index":6755}},{"kind":"Variable","span":{"file_name":"src/main.rs","byte_start":1672,"byte_end":1680,"line_start":63,"line_end":63,"column_start":30,"column_end":38},"ref_id":{"krate":0,"index":4294967073}},{"kind":"Variable","span":{"file_name":"src/main.rs","byte_start":1696,"byte_end":1699,"line_start":64,"line_end":64,"column_start":13,"column_end":16},"ref_id":{"krate":2,"index":29416}},{"kind":"Variable","span":{"file_name":"src/main.rs","byte_start":1696,"byte_end":1699,"line_start":64,"line_end":64,"column_start":13,"column_end":16},"ref_id":{"krate":2,"index":29416}},{"kind":"Function","span":{"file_name":"src/main.rs","byte_start":1733,"byte_end":1740,"line_start":65,"line_end":65,"column_start":26,"column_end":33},"ref_id":{"krate":46,"index":9}},{"kind":"Variable","span":{"file_name":"src/main.rs","byte_start":1724,"byte_end":1732,"line_start":65,"line_end":65,"column_start":17,"column_end":25},"ref_id":{"krate":0,"index":4294967157}},{"kind":"Variable","span":{"file_name":"src/main.rs","byte_start":1749,"byte_end":1759,"line_start":65,"line_end":65,"column_start":42,"column_end":52},"ref_id":{"krate":19,"index":4511}},{"kind":"Mod","span":{"file_name":"src/main.rs","byte_start":1741,"byte_end":1747,"line_start":65,"line_end":65,"column_start":34,"column_end":40},"ref_id":{"krate":15,"index":70}},{"kind":"Function","span":{"file_name":"src/main.rs","byte_start":1787,"byte_end":1794,"line_start":66,"line_end":66,"column_start":26,"column_end":33},"ref_id":{"krate":46,"index":9}},{"kind":"Variable","span":{"file_name":"src/main.rs","byte_start":1778,"byte_end":1786,"line_start":66,"line_end":66,"column_start":17,"column_end":25},"ref_id":{"krate":0,"index":4294967157}},{"kind":"Variable","span":{"file_name":"src/main.rs","byte_start":1851,"byte_end":1859,"line_start":66,"line_end":66,"column_start":90,"column_end":98},"ref_id":{"krate":0,"index":4294967073}},{"kind":"Variable","span":{"file_name":"src/main.rs","byte_start":1886,"byte_end":1888,"line_start":67,"line_end":67,"column_start":24,"column_end":26},"ref_id":{"krate":2,"index":29413}},{"kind":"Variable","span":{"file_name":"src/main.rs","byte_start":1889,"byte_end":1897,"line_start":67,"line_end":67,"column_start":27,"column_end":35},"ref_id":{"krate":0,"index":4294967157}},{"kind":"Variable","span":{"file_name":"src/main.rs","byte_start":1926,"byte_end":1928,"line_start":69,"line_end":69,"column_start":13,"column_end":15},"ref_id":{"krate":2,"index":29413}},{"kind":"Variable","span":{"file_name":"src/main.rs","byte_start":1926,"byte_end":1928,"line_start":69,"line_end":69,"column_start":13,"column_end":15},"ref_id":{"krate":2,"index":29413}},{"kind":"Function","span":{"file_name":"src/main.rs","byte_start":1945,"byte_end":1949,"line_start":69,"line_end":69,"column_start":32,"column_end":36},"ref_id":{"krate":5,"index":3865}},{"kind":"Variable","span":{"file_name":"src/main.rs","byte_start":1937,"byte_end":1944,"line_start":69,"line_end":69,"column_start":24,"column_end":31},"ref_id":{"krate":0,"index":4294967078}},{"kind":"Variable","span":{"file_name":"src/main.rs","byte_start":1950,"byte_end":1951,"line_start":69,"line_end":69,"column_start":37,"column_end":38},"ref_id":{"krate":0,"index":4294967036}},{"kind":"Variable","span":{"file_name":"src/main.rs","byte_start":1989,"byte_end":1996,"line_start":73,"line_end":73,"column_start":17,"column_end":24},"ref_id":{"krate":0,"index":4294967078}},{"kind":"Variable","span":{"file_name":"src/main.rs","byte_start":2015,"byte_end":2022,"line_start":74,"line_end":74,"column_start":15,"column_end":22},"ref_id":{"krate":0,"index":4294967078}},{"kind":"Variable","span":{"file_name":"src/main.rs","byte_start":2038,"byte_end":2039,"line_start":75,"line_end":75,"column_start":9,"column_end":10},"ref_id":{"krate":0,"index":4294967024}},{"kind":"Function","span":{"file_name":"src/main.rs","byte_start":2042,"byte_end":2045,"line_start":75,"line_end":75,"column_start":13,"column_end":16},"ref_id":{"krate":0,"index":12}},{"kind":"Variable","span":{"file_name":"src/main.rs","byte_start":2046,"byte_end":2047,"line_start":75,"line_end":75,"column_start":17,"column_end":18},"ref_id":{"krate":0,"index":4294967024}},{"kind":"Variable","span":{"file_name":"src/main.rs","byte_start":2050,"byte_end":2051,"line_start":75,"line_end":75,"column_start":21,"column_end":22},"ref_id":{"krate":0,"index":4294967019}},{"kind":"Function","span":{"file_name":"src/main.rs","byte_start":2074,"byte_end":2081,"line_start":78,"line_end":78,"column_start":14,"column_end":21},"ref_id":{"krate":46,"index":9}},{"kind":"Variable","span":{"file_name":"src/main.rs","byte_start":2065,"byte_end":2073,"line_start":78,"line_end":78,"column_start":5,"column_end":13},"ref_id":{"krate":0,"index":4294967157}},{"kind":"Variable","span":{"file_name":"src/main.rs","byte_start":2090,"byte_end":2092,"line_start":78,"line_end":78,"column_start":30,"column_end":32},"ref_id":{"krate":19,"index":4475}},{"kind":"Mod","span":{"file_name":"src/main.rs","byte_start":2082,"byte_end":2088,"line_start":78,"line_end":78,"column_start":22,"column_end":28},"ref_id":{"krate":15,"index":70}},{"kind":"Function","span":{"file_name":"src/main.rs","byte_start":2108,"byte_end":2115,"line_start":79,"line_end":79,"column_start":14,"column_end":21},"ref_id":{"krate":46,"index":9}},{"kind":"Variable","span":{"file_name":"src/main.rs","byte_start":2099,"byte_end":2107,"line_start":79,"line_end":79,"column_start":5,"column_end":13},"ref_id":{"krate":0,"index":4294967157}},{"kind":"Function","span":{"file_name":"src/main.rs","byte_start":2162,"byte_end":2169,"line_start":80,"line_end":80,"column_start":14,"column_end":21},"ref_id":{"krate":46,"index":9}},{"kind":"Variable","span":{"file_name":"src/main.rs","byte_start":2153,"byte_end":2161,"line_start":80,"line_end":80,"column_start":5,"column_end":13},"ref_id":{"krate":0,"index":4294967157}},{"kind":"Variable","span":{"file_name":"src/main.rs","byte_start":2244,"byte_end":2251,"line_start":80,"line_end":80,"column_start":96,"column_end":103},"ref_id":{"krate":0,"index":4294967078}},{"kind":"Variable","span":{"file_name":"src/main.rs","byte_start":2253,"byte_end":2254,"line_start":80,"line_end":80,"column_start":105,"column_end":106},"ref_id":{"krate":0,"index":4294967024}},{"kind":"Variable","span":{"file_name":"src/main.rs","byte_start":2262,"byte_end":2264,"line_start":81,"line_end":81,"column_start":5,"column_end":7},"ref_id":{"krate":2,"index":29413}},{"kind":"Variable","span":{"file_name":"src/main.rs","byte_start":2265,"byte_end":2273,"line_start":81,"line_end":81,"column_start":8,"column_end":16},"ref_id":{"krate":0,"index":4294967157}},{"kind":"Function","span":{"file_name":"src/main.rs","byte_start":2319,"byte_end":2322,"line_start":85,"line_end":85,"column_start":30,"column_end":33},"ref_id":{"krate":47,"index":40}},{"kind":"Type","span":{"file_name":"src/main.rs","byte_start":2311,"byte_end":2317,"line_start":85,"line_end":85,"column_start":22,"column_end":28},"ref_id":{"krate":47,"index":37}},{"kind":"Function","span":{"file_name":"src/main.rs","byte_start":2338,"byte_end":2341,"line_start":87,"line_end":87,"column_start":12,"column_end":15},"ref_id":{"krate":47,"index":47}},{"kind":"Variable","span":{"file_name":"src/main.rs","byte_start":2331,"byte_end":2337,"line_start":87,"line_end":87,"column_start":5,"column_end":11},"ref_id":{"krate":0,"index":4294966976}},{"kind":"Function","span":{"file_name":"src/main.rs","byte_start":2347,"byte_end":2355,"line_start":87,"line_end":87,"column_start":21,"column_end":29},"ref_id":{"krate":0,"index":13}},{"kind":"Function","span":{"file_name":"src/main.rs","byte_start":2377,"byte_end":2381,"line_start":88,"line_end":88,"column_start":12,"column_end":16},"ref_id":{"krate":47,"index":51}},{"kind":"Variable","span":{"file_name":"src/main.rs","byte_start":2370,"byte_end":2376,"line_start":88,"line_end":88,"column_start":5,"column_end":11},"ref_id":{"krate":0,"index":4294966976}},{"kind":"Function","span":{"file_name":"src/main.rs","byte_start":2390,"byte_end":2398,"line_start":88,"line_end":88,"column_start":25,"column_end":33},"ref_id":{"krate":0,"index":14}},{"kind":"Function","span":{"file_name":"src/main.rs","byte_start":2508,"byte_end":2514,"line_start":90,"line_end":90,"column_start":48,"column_end":54},"ref_id":{"krate":2,"index":5410}},{"kind":"Function","span":{"file_name":"src/main.rs","byte_start":2485,"byte_end":2489,"line_start":90,"line_end":90,"column_start":25,"column_end":29},"ref_id":{"krate":15,"index":416}},{"kind":"Function","span":{"file_name":"src/main.rs","byte_start":2471,"byte_end":2474,"line_start":90,"line_end":90,"column_start":11,"column_end":14},"ref_id":{"krate":15,"index":415}},{"kind":"Type","span":{"file_name":"src/main.rs","byte_start":2465,"byte_end":2469,"line_start":90,"line_end":90,"column_start":5,"column_end":9},"ref_id":{"krate":15,"index":402}},{"kind":"Function","span":{"file_name":"src/main.rs","byte_start":2475,"byte_end":2483,"line_start":90,"line_end":90,"column_start":15,"column_end":23},"ref_id":{"krate":0,"index":13}}],"macro_refs":[],"relations":[]}